multicall3-0.1.4.dist-info/METADATA
multicall3-0.1.4.dist-info/WHEEL
multicall3/__init__.py
multicall3/abi.py
multicall3-0.1.4.dist-info/RECORD
