Metadata-Version: 2.1
Name: multicall3
Version: 0.1.4
Summary: Python 3 interface Mutlicall3 smart contract
Author-Email: pyk <gm@pyk.sh>
License: MIT
Requires-Python: >=3.8
Requires-Dist: web3>=6.11
